hatch_nodejs_version/__init__.py
hatch_nodejs_version/_version.py
hatch_nodejs_version/hooks.py
hatch_nodejs_version/metadata_source.py
hatch_nodejs_version/version_source.py
hatch_nodejs_version-0.4.0.dist-info/METADATA
hatch_nodejs_version-0.4.0.dist-info/WHEEL
hatch_nodejs_version-0.4.0.dist-info/entry_points.txt
hatch_nodejs_version-0.4.0.dist-info/licenses/LICENSE.txt
hatch_nodejs_version-0.4.0.dist-info/RECORD
