Metadata-Version: 2.4
Name: hatch-nodejs-version
Version: 0.4.0
Summary: Hatch plugin for versioning from a package.json file
Project-URL: Homepage, https://github.com/agoose77/hatch-nodejs-version
Project-URL: Issue Tracker, https://github.com/agoose77/hatch-nodejs-version/issues
Project-URL: Source Code, https://github.com/agoose77/hatch-nodejs-version
Author: Frédéric Collonval
Author-email: Angus Hollands <goosey15@gmail.com>
License: MIT
License-File: LICENSE.txt
Classifier: Framework :: Hatch
Classifier: Programming Language :: Python :: 3.9
Classifier: Programming Language :: Python :: 3.10
Classifier: Programming Language :: Python :: 3.11
Classifier: Programming Language :: Python :: 3.12
Classifier: Programming Language :: Python :: 3.13
Requires-Python: >=3.9
Requires-Dist: hatchling>=0.21.0
